hexly/__init__.py
hexly/config.py
hexly/encoding.py
hexly/hexview.py
hexly/style.css
hexly/templates.py
hexly-0.0.4.dist-info/LICENSE
hexly-0.0.4.dist-info/METADATA
hexly-0.0.4.dist-info/WHEEL
hexly-0.0.4.dist-info/RECORD
