Metadata-Version: 2.1
Name: hexly
Version: 0.0.4
Summary: A hex viewer for Jupyter notebooks
Author: Shad Sharma
Author-email: shadanan@gmail.com
Requires-Python: >=3.12,<4.0
Classifier: Programming Language :: Python :: 3
Classifier: Programming Language :: Python :: 3.12
